parcels/__init__.py
parcels/_compat.py
parcels/_index_search.py
parcels/_interpolation.py
parcels/_typing.py
parcels/_version.py
parcels/_version_setup.py
parcels/field.py
parcels/fieldfilebuffer.py
parcels/fieldset.py
parcels/grid.py
parcels/gridset.py
parcels/kernel.py
parcels/particle.py
parcels/particledata.py
parcels/particlefile.py
parcels/particleset.py
parcels/rng.py
parcels/application_kernels/EOSseawaterproperties.py
parcels/application_kernels/TEOSseawaterdensity.py
parcels/application_kernels/__init__.py
parcels/application_kernels/advection.py
parcels/application_kernels/advectiondiffusion.py
parcels/application_kernels/interaction.py
parcels/compilation/__init__.py
parcels/compilation/codecompiler.py
parcels/compilation/codegenerator.py
parcels/include/index_search.h
parcels/include/interpolation_utils.h
parcels/include/parcels.h
parcels/include/random.h
parcels/interaction/__init__.py
parcels/interaction/interactionkernel.py
parcels/interaction/neighborsearch/__init__.py
parcels/interaction/neighborsearch/base.py
parcels/interaction/neighborsearch/basehash.py
parcels/interaction/neighborsearch/bruteforce.py
parcels/interaction/neighborsearch/distanceutils.py
parcels/interaction/neighborsearch/hashflat.py
parcels/interaction/neighborsearch/hashspherical.py
parcels/interaction/neighborsearch/kdtreeflat.py
parcels/tools/__init__.py
parcels/tools/_helpers.py
parcels/tools/converters.py
parcels/tools/exampledata_utils.py
parcels/tools/global_statics.py
parcels/tools/interpolation_utils.py
parcels/tools/loggers.py
parcels/tools/statuscodes.py
parcels/tools/timer.py
parcels/tools/warnings.py
parcels-3.1.4.dist-info/licenses/LICENSE.md
parcels-3.1.4.dist-info/METADATA
parcels-3.1.4.dist-info/WHEEL
parcels-3.1.4.dist-info/top_level.txt
parcels-3.1.4.dist-info/RECORD
