Metadata-Version: 2.4
Name: parcels
Version: 3.1.4
Summary: Framework for Lagrangian tracking of virtual ocean particles in the petascale age.
Author: oceanparcels.org team
License: The MIT License (MIT)
Project-URL: homepage, https://oceanparcels.org/
Project-URL: repository, https://github.com/OceanParcels/parcels
Project-URL: Tracker, https://github.com/OceanParcels/parcels/issues
Classifier: License :: OSI Approved :: MIT License
Classifier: Programming Language :: Python :: 3.10
Classifier: Programming Language :: Python :: 3.11
Classifier: Programming Language :: Python :: 3.12
Classifier: Programming Language :: Python :: 3.13
Classifier: Operating System :: OS Independent
Classifier: Topic :: Scientific/Engineering
Classifier: Intended Audience :: Science/Research
Requires-Python: >=3.10
License-File: LICENSE.md
Requires-Dist: cgen
Requires-Dist: cftime
Requires-Dist: numpy>=1.11
Requires-Dist: dask
Requires-Dist: psutil
Requires-Dist: netCDF4>=1.1.9
Requires-Dist: zarr!=2.18.0,<3,>=2.11.0
Requires-Dist: tqdm
Requires-Dist: pymbolic
Requires-Dist: pytest
Requires-Dist: scipy>=0.16.0
Requires-Dist: xarray>=0.10.8
Dynamic: license-file
